{"BTC":{"id":1,"name":"Bitcoin","symbol":"BTC","slug":"bitcoin","num_market_pairs":9023,"date_added":"2013-04-28T00:00:00.000Z","tags":["mineable","pow","sha-256","store-of-value","state-channels","coinbase-ventures-portfolio","three-arrows-capital-portfolio","polychain-capital-portfolio","binance-labs-portfolio","arrington-xrp-capital","blockchain-capital-portfolio","boostvc-portfolio","cms-holdings-portfolio","dcg-portfolio","dragonfly-capital-portfolio","electric-capital-portfolio","fabric-ventures-portfolio","framework-ventures","galaxy-digital-portfolio","huobi-capital","alameda-research-portfolio","a16z-portfolio","1confirmation-portfolio","winklevoss-capital","usv-portfolio","placeholder-ventures-portfolio","pantera-capital-portfolio","multicoin-capital-portfolio","paradigm-xzy-screener"],"max_supply":21000000,"circulating_supply":18758037,"total_supply":18758037,"is_active":1,"platform":null,"cmc_rank":1,"is_fiat":0,"last_updated":"2021-07-16T15:55:02.000Z","quote":{"USD":{"price":32141.78623687477,"volume_24h":24517795436.103992,"percent_change_1h":0.67822961,"percent_change_24h":1.35440274,"percent_change_7d":-4.30150705,"percent_change_30d":-17.09935647,"percent_change_60d":-25.92886685,"percent_change_90d":-46.9369819,"market_cap":602916815477.3877,"last_updated":"2021-07-16T15:55:02.000Z"}}},"SBD":{"id":1312,"name":"Steem Dollars","symbol":"SBD","slug":"steem-dollars","num_market_pairs":5,"date_added":"2016-07-18T00:00:00.000Z","tags":["media","content-creation","stablecoin"],"max_supply":null,"circulating_supply":8197016.795,"total_supply":8197016.795,"is_active":1,"platform":null,"cmc_rank":400,"is_fiat":0,"last_updated":"2021-07-16T15:55:04.000Z","quote":{"USD":{"price":6.14809648549911,"volume_24h":12671415.11692662,"percent_change_1h":0.26729094,"percent_change_24h":-3.96667763,"percent_change_7d":5.62100385,"percent_change_30d":-1.04046825,"percent_change_60d":26.4296706,"percent_change_90d":-33.24950108,"market_cap":50396050.14891668,"last_updated":"2021-07-16T15:55:04.000Z"}}},"STEEM":{"id":1230,"name":"Steem","symbol":"STEEM","slug":"steem","num_market_pairs":31,"date_added":"2016-04-18T00:00:00.000Z","tags":["media","content-creation"],"max_supply":null,"circulating_supply":390737853.6,"total_supply":407711947.6,"is_active":1,"platform":null,"cmc_rank":172,"is_fiat":0,"last_updated":"2021-07-16T15:55:04.000Z","quote":{"USD":{"price":0.38530409764287,"volume_24h":9088991.43655358,"percent_change_1h":0.10101989,"percent_change_24h":-4.80073278,"percent_change_7d":6.53659278,"percent_change_30d":-4.9704011,"percent_change_60d":-47.79888091,"percent_change_90d":-67.59850799,"market_cap":150552896.09625986,"last_updated":"2021-07-16T15:55:04.000Z"}}},"TRX":{"id":1958,"name":"TRON","symbol":"TRX","slug":"tron","num_market_pairs":502,"date_added":"2017-09-13T00:00:00.000Z","tags":["media","payments"],"max_supply":null,"circulating_supply":71659657369.49,"total_supply":100850743811.662,"is_active":1,"platform":null,"cmc_rank":25,"is_fiat":0,"last_updated":"2021-07-16T15:55:07.000Z","quote":{"USD":{"price":0.05760943719614,"volume_24h":686867191.132364,"percent_change_1h":0.73685429,"percent_change_24h":-1.15637361,"percent_change_7d":-7.57105109,"percent_change_30d":-17.29846757,"percent_change_60d":-49.08877365,"percent_change_90d":-63.17797181,"market_cap":4128272530.7245455,"last_updated":"2021-07-16T15:55:07.000Z"}}},"USDT":{"id":825,"name":"Tether","symbol":"USDT","slug":"tether","num_market_pairs":14455,"date_added":"2015-02-25T00:00:00.000Z","tags":["payments","stablecoin","stablecoin-asset-backed","avalanche-ecosystem","solana-ecosystem"],"max_supply":null,"circulating_supply":62019248695.48168,"total_supply":64469767616.826355,"platform":{"id":1027,"name":"Ethereum","symbol":"ETH","slug":"ethereum","token_address":"0xdac17f958d2ee523a2206206994597c13d831ec7"},"is_active":1,"cmc_rank":3,"is_fiat":0,"last_updated":"2021-07-16T15:54:29.000Z","quote":{"USD":{"price":1.0002523346109,"volume_24h":47465336769.36624,"percent_change_1h":-0.01032253,"percent_change_24h":0.02097545,"percent_change_7d":0.04218595,"percent_change_30d":-0.00267777,"percent_change_60d":0.0384879,"percent_change_90d":-0.58195541,"market_cap":62034898298.46957,"last_updated":"2021-07-16T15:54:29.000Z"}}}}