{"BTC":{"id":1,"name":"Bitcoin","symbol":"BTC","slug":"bitcoin","num_market_pairs":8530,"date_added":"2013-04-28T00:00:00.000Z","tags":["mineable","pow","sha-256","store-of-value","state-channels","coinbase-ventures-portfolio","three-arrows-capital-portfolio","polychain-capital-portfolio","binance-labs-portfolio","arrington-xrp-capital","blockchain-capital-portfolio","boostvc-portfolio","cms-holdings-portfolio","dcg-portfolio","dragonfly-capital-portfolio","electric-capital-portfolio","fabric-ventures-portfolio","framework-ventures","galaxy-digital-portfolio","huobi-capital","alameda-research-portfolio","a16z-portfolio","1confirmation-portfolio","winklevoss-capital","usv-portfolio","placeholder-ventures-portfolio","pantera-capital-portfolio","multicoin-capital-portfolio","paradigm-xzy-screener"],"max_supply":21000000,"circulating_supply":18834737,"total_supply":18834737,"is_active":1,"platform":null,"cmc_rank":1,"is_fiat":0,"last_updated":"2021-10-04T21:39:02.000Z","quote":{"USD":{"price":48944.52387390227,"volume_24h":32835633079.860462,"percent_change_1h":-0.47959175,"percent_change_24h":2.16829467,"percent_change_7d":13.89132467,"percent_change_30d":-2.45325663,"percent_change_60d":19.25122208,"percent_change_90d":44.40834419,"market_cap":921857234755.1704,"market_cap_dominance":42.9969,"fully_diluted_market_cap":1027835001351.95,"last_updated":"2021-10-04T21:39:02.000Z"}}},"SBD":{"id":1312,"name":"Steem Dollars","symbol":"SBD","slug":"steem-dollars","num_market_pairs":5,"date_added":"2016-07-18T00:00:00.000Z","tags":["media","content-creation","stablecoin"],"max_supply":null,"circulating_supply":9118393.802,"total_supply":9118393.802,"is_active":1,"platform":null,"cmc_rank":480,"is_fiat":0,"last_updated":"2021-10-04T21:39:04.000Z","quote":{"USD":{"price":7.04935155764506,"volume_24h":12967233.37256424,"percent_change_1h":0.12703647,"percent_change_24h":-2.09796468,"percent_change_7d":11.80781121,"percent_change_30d":-22.18353722,"percent_change_60d":-0.28055132,"percent_change_90d":12.96299428,"market_cap":64278763.55134975,"market_cap_dominance":0.003,"fully_diluted_market_cap":64278763.55,"last_updated":"2021-10-04T21:39:04.000Z"}}},"STEEM":{"id":1230,"name":"Steem","symbol":"STEEM","slug":"steem","num_market_pairs":31,"date_added":"2016-04-18T00:00:00.000Z","tags":["media","content-creation"],"max_supply":null,"circulating_supply":391549040.223,"total_supply":408523134.223,"is_active":1,"platform":null,"cmc_rank":193,"is_fiat":0,"last_updated":"2021-10-04T21:39:04.000Z","quote":{"USD":{"price":0.56855433193351,"volume_24h":39216894.53860172,"percent_change_1h":1.16726113,"percent_change_24h":2.94962961,"percent_change_7d":18.39948457,"percent_change_30d":-22.10745109,"percent_change_60d":14.14689321,"percent_change_90d":47.53739305,"market_cap":222616902.9831948,"market_cap_dominance":0.0104,"fully_diluted_market_cap":232267597.66,"last_updated":"2021-10-04T21:39:04.000Z"}}},"TRX":{"id":1958,"name":"TRON","symbol":"TRX","slug":"tron","num_market_pairs":531,"date_added":"2017-09-13T00:00:00.000Z","tags":["media","payments","binance-smart-chain"],"max_supply":null,"circulating_supply":71659657369.49,"total_supply":100850743811.662,"is_active":1,"platform":null,"cmc_rank":30,"is_fiat":0,"last_updated":"2021-10-04T21:38:09.000Z","quote":{"USD":{"price":0.0923913940731,"volume_24h":1151085293.2239912,"percent_change_1h":-0.07494467,"percent_change_24h":-2.15394528,"percent_change_7d":5.3774831,"percent_change_30d":-9.08294196,"percent_change_60d":31.24775707,"percent_change_90d":43.965786,"market_cap":6620735643.167875,"market_cap_dominance":0.3088,"fully_diluted_market_cap":9317740814.07,"last_updated":"2021-10-04T21:38:09.000Z"}}},"USDT":{"id":825,"name":"Tether","symbol":"USDT","slug":"tether","num_market_pairs":18567,"date_added":"2015-02-25T00:00:00.000Z","tags":["payments","stablecoin","stablecoin-asset-backed","binance-smart-chain","avalanche-ecosystem","solana-ecosystem"],"max_supply":null,"circulating_supply":68024069674.7408,"total_supply":71385677474.96931,"platform":{"id":1027,"name":"Ethereum","symbol":"ETH","slug":"ethereum","token_address":"0xdac17f958d2ee523a2206206994597c13d831ec7"},"is_active":1,"cmc_rank":5,"is_fiat":0,"last_updated":"2021-10-04T21:38:09.000Z","quote":{"USD":{"price":0.99961400404813,"volume_24h":73257035059.25983,"percent_change_1h":-0.0454417,"percent_change_24h":-0.05351263,"percent_change_7d":-0.08729722,"percent_change_30d":-0.0877325,"percent_change_60d":-0.05843855,"percent_change_90d":-0.07262531,"market_cap":67997812659.21662,"market_cap_dominance":3.1715,"fully_diluted_market_cap":71358122892.44,"last_updated":"2021-10-04T21:38:09.000Z"}}}}