{"BTC":{"id":1,"name":"Bitcoin","symbol":"BTC","slug":"bitcoin","num_market_pairs":8912,"date_added":"2013-04-28T00:00:00.000Z","tags":["mineable","pow","sha-256","store-of-value","state-channels","coinbase-ventures-portfolio","three-arrows-capital-portfolio","polychain-capital-portfolio","binance-labs-portfolio","arrington-xrp-capital","blockchain-capital-portfolio","boostvc-portfolio","cms-holdings-portfolio","dcg-portfolio","dragonfly-capital-portfolio","electric-capital-portfolio","fabric-ventures-portfolio","framework-ventures","galaxy-digital-portfolio","huobi-capital","alameda-research-portfolio","a16z-portfolio","1confirmation-portfolio","winklevoss-capital","usv-portfolio","placeholder-ventures-portfolio","pantera-capital-portfolio","multicoin-capital-portfolio","paradigm-xzy-screener"],"max_supply":21000000,"circulating_supply":18789925,"total_supply":18789925,"is_active":1,"platform":null,"cmc_rank":1,"is_fiat":0,"last_updated":"2021-08-18T15:54:02.000Z","quote":{"USD":{"price":45740.73775459668,"volume_24h":33597219620.40353,"percent_change_1h":0.89442544,"percent_change_24h":-0.09644805,"percent_change_7d":-1.64902344,"percent_change_30d":48.64629268,"percent_change_60d":26.88116434,"percent_change_90d":10.84772659,"market_cap":859465031853.54,"market_cap_dominance":44.1246,"fully_diluted_market_cap":960555492846.53,"last_updated":"2021-08-18T15:54:02.000Z"}}},"SBD":{"id":1312,"name":"Steem Dollars","symbol":"SBD","slug":"steem-dollars","num_market_pairs":5,"date_added":"2016-07-18T00:00:00.000Z","tags":["media","content-creation","stablecoin"],"max_supply":null,"circulating_supply":8526257.875,"total_supply":8526257.875,"is_active":1,"platform":null,"cmc_rank":453,"is_fiat":0,"last_updated":"2021-08-18T15:54:04.000Z","quote":{"USD":{"price":7.45482009650507,"volume_24h":46263680.03339548,"percent_change_1h":0.17520137,"percent_change_24h":-2.86533195,"percent_change_7d":-4.74962594,"percent_change_30d":29.16187778,"percent_change_60d":27.56594804,"percent_change_90d":-39.57200289,"market_cap":63561718.554534614,"market_cap_dominance":0.0033,"fully_diluted_market_cap":63561718.55,"last_updated":"2021-08-18T15:54:04.000Z"}}},"STEEM":{"id":1230,"name":"Steem","symbol":"STEEM","slug":"steem","num_market_pairs":31,"date_added":"2016-04-18T00:00:00.000Z","tags":["media","content-creation"],"max_supply":null,"circulating_supply":386459382.992,"total_supply":403433476.992,"is_active":1,"platform":null,"cmc_rank":183,"is_fiat":0,"last_updated":"2021-08-18T15:54:03.000Z","quote":{"USD":{"price":0.5301803746485,"volume_24h":16638792.07281479,"percent_change_1h":0.53689679,"percent_change_24h":-6.99949052,"percent_change_7d":-4.31482851,"percent_change_30d":57.18535831,"percent_change_60d":50.83501931,"percent_change_90d":-29.4295592,"market_cap":204893180.4611267,"market_cap_dominance":0.0106,"fully_diluted_market_cap":213892511.98,"last_updated":"2021-08-18T15:54:03.000Z"}}},"TRX":{"id":1958,"name":"TRON","symbol":"TRX","slug":"tron","num_market_pairs":527,"date_added":"2017-09-13T00:00:00.000Z","tags":["media","payments","binance-smart-chain"],"max_supply":null,"circulating_supply":71659657369.49,"total_supply":100850743811.662,"is_active":1,"platform":null,"cmc_rank":25,"is_fiat":0,"last_updated":"2021-08-18T15:54:08.000Z","quote":{"USD":{"price":0.08610355186019,"volume_24h":1161242037.9986074,"percent_change_1h":0.98778762,"percent_change_24h":-3.49700374,"percent_change_7d":2.72598566,"percent_change_30d":59.74473202,"percent_change_60d":23.05551686,"percent_change_90d":-4.36899212,"market_cap":6170151024.597329,"market_cap_dominance":0.3192,"fully_diluted_market_cap":8683607249.93,"last_updated":"2021-08-18T15:54:08.000Z"}}},"USDT":{"id":825,"name":"Tether","symbol":"USDT","slug":"tether","num_market_pairs":16970,"date_added":"2015-02-25T00:00:00.000Z","tags":["payments","stablecoin","stablecoin-asset-backed","binance-smart-chain","avalanche-ecosystem","solana-ecosystem"],"max_supply":null,"circulating_supply":64056734130.548836,"total_supply":65468847059.56271,"platform":{"id":1027,"name":"Ethereum","symbol":"ETH","slug":"ethereum","token_address":"0xdac17f958d2ee523a2206206994597c13d831ec7"},"is_active":1,"cmc_rank":5,"is_fiat":0,"last_updated":"2021-08-18T15:53:08.000Z","quote":{"USD":{"price":1.00028181393342,"volume_24h":85278001864.70898,"percent_change_1h":0.00986822,"percent_change_24h":0.00777772,"percent_change_7d":-0.04498184,"percent_change_30d":0.01508489,"percent_change_60d":-0.13365384,"percent_change_90d":-0.16943127,"market_cap":64074786210.7562,"market_cap_dominance":3.3147,"fully_diluted_market_cap":65487297092.87,"last_updated":"2021-08-18T15:53:08.000Z"}}}}