{"BTC":{"id":1,"name":"Bitcoin","symbol":"BTC","slug":"bitcoin","num_market_pairs":8942,"date_added":"2013-04-28T00:00:00.000Z","tags":["mineable","pow","sha-256","store-of-value","state-channels","coinbase-ventures-portfolio","three-arrows-capital-portfolio","polychain-capital-portfolio","binance-labs-portfolio","arrington-xrp-capital","blockchain-capital-portfolio","boostvc-portfolio","cms-holdings-portfolio","dcg-portfolio","dragonfly-capital-portfolio","electric-capital-portfolio","fabric-ventures-portfolio","framework-ventures","galaxy-digital-portfolio","huobi-capital","alameda-research-portfolio","a16z-portfolio","1confirmation-portfolio","winklevoss-capital","usv-portfolio","placeholder-ventures-portfolio","pantera-capital-portfolio","multicoin-capital-portfolio","paradigm-xzy-screener"],"max_supply":21000000,"circulating_supply":18777275,"total_supply":18777275,"is_active":1,"platform":null,"cmc_rank":1,"is_fiat":0,"last_updated":"2021-08-05T20:30:02.000Z","quote":{"USD":{"price":40937.50138607738,"volume_24h":34600888994.61854,"percent_change_1h":-0.78370108,"percent_change_24h":3.00451227,"percent_change_7d":2.99186275,"percent_change_30d":20.49422526,"percent_change_60d":14.11287732,"percent_change_90d":-29.14356768,"market_cap":768694721339.2562,"last_updated":"2021-08-05T20:30:02.000Z"}}},"SBD":{"id":1312,"name":"Steem Dollars","symbol":"SBD","slug":"steem-dollars","num_market_pairs":5,"date_added":"2016-07-18T00:00:00.000Z","tags":["media","content-creation","stablecoin"],"max_supply":null,"circulating_supply":8376955.887,"total_supply":8376955.887,"is_active":1,"platform":null,"cmc_rank":426,"is_fiat":0,"last_updated":"2021-08-05T20:30:04.000Z","quote":{"USD":{"price":7.04723643751766,"volume_24h":8481935.84647147,"percent_change_1h":-0.25692565,"percent_change_24h":0.41321422,"percent_change_7d":3.09075692,"percent_change_30d":13.33768363,"percent_change_60d":-6.85651744,"percent_change_90d":-8.37181668,"market_cap":59034388.76234447,"last_updated":"2021-08-05T20:30:04.000Z"}}},"STEEM":{"id":1230,"name":"Steem","symbol":"STEEM","slug":"steem","num_market_pairs":31,"date_added":"2016-04-18T00:00:00.000Z","tags":["media","content-creation"],"max_supply":null,"circulating_supply":388447946.656,"total_supply":405422040.656,"is_active":1,"platform":null,"cmc_rank":176,"is_fiat":0,"last_updated":"2021-08-05T20:30:03.000Z","quote":{"USD":{"price":0.49742807452226,"volume_24h":15089537.13351202,"percent_change_1h":-0.80505379,"percent_change_24h":2.44961416,"percent_change_7d":5.14502909,"percent_change_30d":29.0086957,"percent_change_60d":-8.89986047,"percent_change_90d":-57.82105347,"market_cap":193224914.15721965,"last_updated":"2021-08-05T20:30:03.000Z"}}},"TRX":{"id":1958,"name":"TRON","symbol":"TRX","slug":"tron","num_market_pairs":513,"date_added":"2017-09-13T00:00:00.000Z","tags":["media","payments"],"max_supply":null,"circulating_supply":71659657369.49,"total_supply":100850743811.662,"is_active":1,"platform":null,"cmc_rank":26,"is_fiat":0,"last_updated":"2021-08-05T20:30:08.000Z","quote":{"USD":{"price":0.06988234833506,"volume_24h":1208331469.1782832,"percent_change_1h":-0.32864413,"percent_change_24h":3.32670098,"percent_change_7d":13.85937869,"percent_change_30d":8.06115453,"percent_change_60d":-8.82510088,"percent_change_90d":-53.11538051,"market_cap":5007745137.86575,"last_updated":"2021-08-05T20:30:08.000Z"}}},"USDT":{"id":825,"name":"Tether","symbol":"USDT","slug":"tether","num_market_pairs":16417,"date_added":"2015-02-25T00:00:00.000Z","tags":["payments","stablecoin","stablecoin-asset-backed","avalanche-ecosystem","solana-ecosystem"],"max_supply":null,"circulating_supply":62000121093.688835,"total_supply":64469737785.68351,"platform":{"id":1027,"name":"Ethereum","symbol":"ETH","slug":"ethereum","token_address":"0xdac17f958d2ee523a2206206994597c13d831ec7"},"is_active":1,"cmc_rank":3,"is_fiat":0,"last_updated":"2021-08-05T20:30:07.000Z","quote":{"USD":{"price":1.00024775340855,"volume_24h":66984381014.00632,"percent_change_1h":-0.00186449,"percent_change_24h":0.03358896,"percent_change_7d":-0.03962305,"percent_change_30d":0.01420304,"percent_change_60d":-0.03419943,"percent_change_90d":0.04157848,"market_cap":62015481835.02032,"last_updated":"2021-08-05T20:30:07.000Z"}}}}