{"BTC":{"id":1,"name":"Bitcoin","symbol":"BTC","slug":"bitcoin","num_market_pairs":8856,"date_added":"2013-04-28T00:00:00.000Z","tags":["mineable","pow","sha-256","store-of-value","state-channels","coinbase-ventures-portfolio","three-arrows-capital-portfolio","polychain-capital-portfolio","binance-labs-portfolio","arrington-xrp-capital","blockchain-capital-portfolio","boostvc-portfolio","cms-holdings-portfolio","dcg-portfolio","dragonfly-capital-portfolio","electric-capital-portfolio","fabric-ventures-portfolio","framework-ventures","galaxy-digital-portfolio","huobi-capital","alameda-research-portfolio","a16z-portfolio","1confirmation-portfolio","winklevoss-capital","usv-portfolio","placeholder-ventures-portfolio","pantera-capital-portfolio","multicoin-capital-portfolio","paradigm-xzy-screener"],"max_supply":21000000,"circulating_supply":18800462,"total_supply":18800462,"is_active":1,"platform":null,"cmc_rank":1,"is_fiat":0,"last_updated":"2021-08-29T04:48:12.000Z","quote":{"USD":{"price":48243.480222130165,"volume_24h":28930580218.603123,"percent_change_1h":-0.07840305,"percent_change_24h":-1.55474945,"percent_change_7d":-1.295684,"percent_change_30d":21.24594828,"percent_change_60d":38.82733624,"percent_change_90d":40.20806558,"market_cap":906999716663.9098,"market_cap_dominance":43.781,"fully_diluted_market_cap":1013113084664.73,"last_updated":"2021-08-29T04:48:12.000Z"}}},"SBD":{"id":1312,"name":"Steem Dollars","symbol":"SBD","slug":"steem-dollars","num_market_pairs":5,"date_added":"2016-07-18T00:00:00.000Z","tags":["media","content-creation","stablecoin"],"max_supply":null,"circulating_supply":8659987.755,"total_supply":8659987.755,"is_active":1,"platform":null,"cmc_rank":465,"is_fiat":0,"last_updated":"2021-08-29T04:47:21.000Z","quote":{"USD":{"price":7.84609150890941,"volume_24h":9897409.42238672,"percent_change_1h":0.27430846,"percent_change_24h":-2.25293074,"percent_change_7d":-3.54494363,"percent_change_30d":11.86758051,"percent_change_60d":32.49157686,"percent_change_90d":3.6091345,"market_cap":67947056.39176497,"market_cap_dominance":0.0033,"fully_diluted_market_cap":67947056.39,"last_updated":"2021-08-29T04:47:21.000Z"}}},"STEEM":{"id":1230,"name":"Steem","symbol":"STEEM","slug":"steem","num_market_pairs":31,"date_added":"2016-04-18T00:00:00.000Z","tags":["media","content-creation"],"max_supply":null,"circulating_supply":387458276.885,"total_supply":404432370.885,"is_active":1,"platform":null,"cmc_rank":184,"is_fiat":0,"last_updated":"2021-08-29T04:47:20.000Z","quote":{"USD":{"price":0.56955168598502,"volume_24h":6688063.48709146,"percent_change_1h":-0.38550607,"percent_change_24h":-2.60118329,"percent_change_7d":-0.72860133,"percent_change_30d":17.58841225,"percent_change_60d":61.26498195,"percent_change_90d":12.9797476,"market_cap":220677514.84870246,"market_cap_dominance":0.0107,"fully_diluted_market_cap":230345138.7,"last_updated":"2021-08-29T04:47:20.000Z"}}},"TRX":{"id":1958,"name":"TRON","symbol":"TRX","slug":"tron","num_market_pairs":528,"date_added":"2017-09-13T00:00:00.000Z","tags":["media","payments","binance-smart-chain"],"max_supply":null,"circulating_supply":71659657369.49,"total_supply":100850743811.662,"is_active":1,"platform":null,"cmc_rank":26,"is_fiat":0,"last_updated":"2021-08-29T04:47:43.000Z","quote":{"USD":{"price":0.08764821239557,"volume_24h":1141261592.9107547,"percent_change_1h":-0.00990414,"percent_change_24h":0.46858095,"percent_change_7d":-0.97851509,"percent_change_30d":41.17182892,"percent_change_60d":34.15155737,"percent_change_90d":24.72983365,"market_cap":6280840869.314833,"market_cap_dominance":0.3036,"fully_diluted_market_cap":8839387413.86,"last_updated":"2021-08-29T04:47:43.000Z"}}},"USDT":{"id":825,"name":"Tether","symbol":"USDT","slug":"tether","num_market_pairs":17213,"date_added":"2015-02-25T00:00:00.000Z","tags":["payments","stablecoin","stablecoin-asset-backed","binance-smart-chain","avalanche-ecosystem","solana-ecosystem"],"max_supply":null,"circulating_supply":65489475280.742584,"total_supply":67432085235.95035,"platform":{"id":1027,"name":"Ethereum","symbol":"ETH","slug":"ethereum","token_address":"0xdac17f958d2ee523a2206206994597c13d831ec7"},"is_active":1,"cmc_rank":5,"is_fiat":0,"last_updated":"2021-08-29T04:47:52.000Z","quote":{"USD":{"price":1.00032426018797,"volume_24h":65995286982.01225,"percent_change_1h":-0.03358752,"percent_change_24h":-0.06936589,"percent_change_7d":0.03182274,"percent_change_30d":0.00577792,"percent_change_60d":0.01728944,"percent_change_90d":-0.01711279,"market_cap":65510710910.307175,"market_cap_dominance":3.1622,"fully_diluted_market_cap":67453950776.58,"last_updated":"2021-08-29T04:47:52.000Z"}}}}