{"BTC":{"id":1,"name":"Bitcoin","symbol":"BTC","slug":"bitcoin","num_market_pairs":8764,"date_added":"2013-04-28T00:00:00.000Z","tags":["mineable","pow","sha-256","store-of-value","state-channels","coinbase-ventures-portfolio","three-arrows-capital-portfolio","polychain-capital-portfolio","binance-labs-portfolio","arrington-xrp-capital","blockchain-capital-portfolio","boostvc-portfolio","cms-holdings-portfolio","dcg-portfolio","dragonfly-capital-portfolio","electric-capital-portfolio","fabric-ventures-portfolio","framework-ventures","galaxy-digital-portfolio","huobi-capital","alameda-research-portfolio","a16z-portfolio","1confirmation-portfolio","winklevoss-capital","usv-portfolio","placeholder-ventures-portfolio","pantera-capital-portfolio","multicoin-capital-portfolio","paradigm-xzy-screener"],"max_supply":21000000,"circulating_supply":18822293,"total_supply":18822293,"is_active":1,"platform":null,"cmc_rank":1,"is_fiat":0,"last_updated":"2021-09-21T14:48:02.000Z","quote":{"USD":{"price":42544.11998297478,"volume_24h":42576278993.00869,"percent_change_1h":-1.72111288,"percent_change_24h":-3.17358312,"percent_change_7d":-8.30428406,"percent_change_30d":-12.43495895,"percent_change_60d":31.01959782,"percent_change_90d":25.39868297,"market_cap":800777891746.7063,"market_cap_dominance":42.2993,"fully_diluted_market_cap":893426519642.47,"last_updated":"2021-09-21T14:48:02.000Z"}}},"SBD":{"id":1312,"name":"Steem Dollars","symbol":"SBD","slug":"steem-dollars","num_market_pairs":5,"date_added":"2016-07-18T00:00:00.000Z","tags":["media","content-creation","stablecoin"],"max_supply":null,"circulating_supply":8976621.117,"total_supply":8976621.117,"is_active":1,"platform":null,"cmc_rank":492,"is_fiat":0,"last_updated":"2021-09-21T14:47:09.000Z","quote":{"USD":{"price":6.43663431771639,"volume_24h":29647384.95393715,"percent_change_1h":-1.89620643,"percent_change_24h":-17.64454126,"percent_change_7d":-16.21380226,"percent_change_30d":-17.46156388,"percent_change_60d":8.72488337,"percent_change_90d":66.79720027,"market_cap":57779227.538819835,"market_cap_dominance":0.003,"fully_diluted_market_cap":57779227.54,"last_updated":"2021-09-21T14:47:09.000Z"}}},"STEEM":{"id":1230,"name":"Steem","symbol":"STEEM","slug":"steem","num_market_pairs":31,"date_added":"2016-04-18T00:00:00.000Z","tags":["media","content-creation"],"max_supply":null,"circulating_supply":388553032.504,"total_supply":405527126.504,"is_active":1,"platform":null,"cmc_rank":192,"is_fiat":0,"last_updated":"2021-09-21T14:47:08.000Z","quote":{"USD":{"price":0.50411969729031,"volume_24h":12419042.39140396,"percent_change_1h":-2.14995896,"percent_change_24h":-8.62069653,"percent_change_7d":-17.32913169,"percent_change_30d":-9.68797176,"percent_change_60d":35.82681559,"percent_change_90d":116.22276003,"market_cap":195877237.12714848,"market_cap_dominance":0.0103,"fully_diluted_market_cap":204434212.26,"last_updated":"2021-09-21T14:47:08.000Z"}}},"TRX":{"id":1958,"name":"TRON","symbol":"TRX","slug":"tron","num_market_pairs":540,"date_added":"2017-09-13T00:00:00.000Z","tags":["media","payments","binance-smart-chain"],"max_supply":null,"circulating_supply":71659657369.49,"total_supply":100850743811.662,"is_active":1,"platform":null,"cmc_rank":25,"is_fiat":0,"last_updated":"2021-09-21T14:47:12.000Z","quote":{"USD":{"price":0.09259665508851,"volume_24h":1867103356.033904,"percent_change_1h":-1.82907897,"percent_change_24h":-1.53928843,"percent_change_7d":-21.80118064,"percent_change_30d":5.6068641,"percent_change_60d":68.29708224,"percent_change_90d":65.79249256,"market_cap":6635444577.20347,"market_cap_dominance":0.3494,"fully_diluted_market_cap":9338441540.15,"last_updated":"2021-09-21T14:47:12.000Z"}}},"USDT":{"id":825,"name":"Tether","symbol":"USDT","slug":"tether","num_market_pairs":18422,"date_added":"2015-02-25T00:00:00.000Z","tags":["payments","stablecoin","stablecoin-asset-backed","binance-smart-chain","avalanche-ecosystem","solana-ecosystem"],"max_supply":null,"circulating_supply":68737505886.5308,"total_supply":71335677474.96931,"platform":{"id":1027,"name":"Ethereum","symbol":"ETH","slug":"ethereum","token_address":"0xdac17f958d2ee523a2206206994597c13d831ec7"},"is_active":1,"cmc_rank":3,"is_fiat":0,"last_updated":"2021-09-21T14:47:44.000Z","quote":{"USD":{"price":1.00009968145557,"volume_24h":88320498443.23172,"percent_change_1h":-0.03000607,"percent_change_24h":-0.02128913,"percent_change_7d":-0.0481763,"percent_change_30d":-0.07914756,"percent_change_60d":-0.01297304,"percent_change_90d":-0.08125019,"market_cap":68744357741.16983,"market_cap_dominance":3.6197,"fully_diluted_market_cap":71342788319.13,"last_updated":"2021-09-21T14:47:44.000Z"}}}}