[{"status":"OK","datetime":"2022-01-09T11:29:24.979123","source_commit":"ae6c6c77601436e496a8816ece2cbc6e26fbe3c2","docker_tag":"latest","jussi_num":60580869,"ping":147,"url":"https://api.steemit.com"},{"status":"OK","datetime":"2022-01-09T11:29:25.005999","source_commit":"ae6c6c77601436e496a8816ece2cbc6e26fbe3c2","docker_tag":"latest","jussi_num":60580869,"ping":174,"url":"https://api.steemitdev.com"},{"status":"OK","datetime":"2022-01-09T11:29:25.214916","source_commit":"ae6c6c77601436e496a8816ece2cbc6e26fbe3c2","docker_tag":"latest","jussi_num":60580869,"ping":427,"url":"https://api.justyy.com"},{"message":"Forbidden","ping":78,"url":"https://e51ewpb9dk.execute-api.us-east-1.amazonaws.com/release"},{"status":"OK","datetime":"2022-01-09T11:29:25.117948","source_commit":"ae6c6c77601436e496a8816ece2cbc6e26fbe3c2","docker_tag":"latest","jussi_num":60580869,"ping":323,"url":"https://api.steemyy.com"},{"status":"OK","datetime":"2022-01-09T11:29:25.135422","source_commit":"ae6c6c77601436e496a8816ece2cbc6e26fbe3c2","docker_tag":"latest","jussi_num":60580869,"ping":310,"url":"https://api.steemzzang.com"},{"status":"OK","datetime":"2022-01-09T11:29:26.257442","source_commit":"ae6c6c77601436e496a8816ece2cbc6e26fbe3c2","docker_tag":"latest","jussi_num":60580869,"__version__":{"id":0,"jsonrpc":"2.0","result":{"blockchain_version":"0.23.0","steem_revision":"7cbeff35b26d086a2a7a77df4126782a56133156","fc_revision":"7cbeff35b26d086a2a7a77df4126782a56133156"}},"__server__":"https://api.steemit.com","__serverless_version__":"2021-12-23","ping":1574,"url":"https://x68bp3mesd.execute-api.ap-northeast-1.amazonaws.com/release"},{"status":"FAIL","message":"error sending request for url (https://cn.steems.top/): error trying to connect: tcp connect error: Connection timed out (os error 110)","url":"https://cn.steems.top"},{"status":"OK","datetime":"2022-01-09T11:29:25.427673","source_commit":"ae6c6c77601436e496a8816ece2cbc6e26fbe3c2","docker_tag":"latest","jussi_num":60580869,"__server__":"https://api.worldofxpilar.com","__version__":{"id":0,"jsonrpc":"2.0","result":{"blockchain_version":"0.23.1","steem_revision":"46c7d93db350e8b031a81626e727c92b27d7348b","fc_revision":"46c7d93db350e8b031a81626e727c92b27d7348b"}},"__serverless_version__":"2021-12-24","ping":792,"url":"https://justyy.azurewebsites.net/api/steem"},{"status":"OK","datetime":"2022-01-09T11:29:25.016210","source_commit":"ae6c6c77601436e496a8816ece2cbc6e26fbe3c2","docker_tag":"latest","jussi_num":60580869,"__server__":"https://api.steemit.com","__version__":{"id":0,"jsonrpc":"2.0","result":{"blockchain_version":"0.23.0","steem_revision":"7cbeff35b26d086a2a7a77df4126782a56133156","fc_revision":"7cbeff35b26d086a2a7a77df4126782a56133156"}},"__country__":"US","__serverless_version__":"2021-12-23","ping":187,"url":"https://steem.justyy.workers.dev"},{"status":"OK","datetime":"2022-01-09T11:29:25.200342","source_commit":"ae6c6c77601436e496a8816ece2cbc6e26fbe3c2","docker_tag":"latest","jussi_num":60580803,"ping":416,"url":"https://steem.ecosynthesizer.com"},{"status":"OK","datetime":"2022-01-09T11:29:25.367540","source_commit":"ae6c6c77601436e496a8816ece2cbc6e26fbe3c2","docker_tag":"latest","jussi_num":60580869,"ping":641,"url":"https://steem.61bts.com"},{"status":"OK","datetime":"2022-01-09T11:29:25.269490","source_commit":"ae6c6c77601436e496a8816ece2cbc6e26fbe3c2","docker_tag":"latest","jussi_num":60580866,"ping":493,"url":"https://api.steem.buzz"},{"status":"OK","datetime":"2022-01-09T11:29:27.553858","source_commit":"ae6c6c77601436e496a8816ece2cbc6e26fbe3c2","docker_tag":"latest","jussi_num":60580869,"ping":2914,"url":"https://api.steem.fans"}]