{"BTC":{"id":1,"name":"Bitcoin","symbol":"BTC","slug":"bitcoin","num_market_pairs":8997,"date_added":"2013-04-28T00:00:00.000Z","tags":["mineable","pow","sha-256","store-of-value","state-channels","coinbase-ventures-portfolio","three-arrows-capital-portfolio","polychain-capital-portfolio","binance-labs-portfolio","arrington-xrp-capital","blockchain-capital-portfolio","boostvc-portfolio","cms-holdings-portfolio","dcg-portfolio","dragonfly-capital-portfolio","electric-capital-portfolio","fabric-ventures-portfolio","framework-ventures","galaxy-digital-portfolio","huobi-capital","alameda-research-portfolio","a16z-portfolio","1confirmation-portfolio","winklevoss-capital","usv-portfolio","placeholder-ventures-portfolio","pantera-capital-portfolio","multicoin-capital-portfolio","paradigm-xzy-screener"],"max_supply":21000000,"circulating_supply":18767081,"total_supply":18767081,"is_active":1,"platform":null,"cmc_rank":1,"is_fiat":0,"last_updated":"2021-07-26T10:28:02.000Z","quote":{"USD":{"price":38166.32423815002,"volume_24h":37162293810.83913,"percent_change_1h":-0.33526267,"percent_change_24h":10.5068559,"percent_change_7d":21.83981812,"percent_change_30d":22.72432489,"percent_change_60d":-3.07012271,"percent_change_90d":-30.11419598,"market_cap":716270498449.6246,"last_updated":"2021-07-26T10:28:02.000Z"}}},"SBD":{"id":1312,"name":"Steem Dollars","symbol":"SBD","slug":"steem-dollars","num_market_pairs":5,"date_added":"2016-07-18T00:00:00.000Z","tags":["media","content-creation","stablecoin"],"max_supply":null,"circulating_supply":8274172.964,"total_supply":8274172.964,"is_active":1,"platform":null,"cmc_rank":405,"is_fiat":0,"last_updated":"2021-07-26T10:28:04.000Z","quote":{"USD":{"price":6.67925285893967,"volume_24h":42098508.77429181,"percent_change_1h":-0.04832549,"percent_change_24h":5.63287374,"percent_change_7d":12.66295891,"percent_change_30d":56.9637833,"percent_change_60d":-27.18312313,"percent_change_90d":-18.04786522,"market_cap":55265293.425158314,"last_updated":"2021-07-26T10:28:04.000Z"}}},"STEEM":{"id":1230,"name":"Steem","symbol":"STEEM","slug":"steem","num_market_pairs":31,"date_added":"2016-04-18T00:00:00.000Z","tags":["media","content-creation"],"max_supply":null,"circulating_supply":392387766.26,"total_supply":409361860.26,"is_active":1,"platform":null,"cmc_rank":177,"is_fiat":0,"last_updated":"2021-07-26T10:28:03.000Z","quote":{"USD":{"price":0.39965618251094,"volume_24h":16194678.27006248,"percent_change_1h":0.06369773,"percent_change_24h":4.07902468,"percent_change_7d":14.6150283,"percent_change_30d":71.13981192,"percent_change_60d":-37.52547398,"percent_change_90d":-56.19448488,"market_cap":156820196.7274666,"last_updated":"2021-07-26T10:28:03.000Z"}}},"TRX":{"id":1958,"name":"TRON","symbol":"TRX","slug":"tron","num_market_pairs":498,"date_added":"2017-09-13T00:00:00.000Z","tags":["media","payments"],"max_supply":null,"circulating_supply":71659657369.49,"total_supply":100850743811.662,"is_active":1,"platform":null,"cmc_rank":25,"is_fiat":0,"last_updated":"2021-07-26T10:27:08.000Z","quote":{"USD":{"price":0.06138869502488,"volume_24h":971528974.1922083,"percent_change_1h":-0.28106358,"percent_change_24h":6.55024866,"percent_change_7d":10.58886956,"percent_change_30d":1.73307411,"percent_change_60d":-24.33166894,"percent_change_90d":-51.84512898,"market_cap":4399092851.843017,"last_updated":"2021-07-26T10:27:08.000Z"}}},"USDT":{"id":825,"name":"Tether","symbol":"USDT","slug":"tether","num_market_pairs":14730,"date_added":"2015-02-25T00:00:00.000Z","tags":["payments","stablecoin","stablecoin-asset-backed","avalanche-ecosystem","solana-ecosystem"],"max_supply":null,"circulating_supply":61810332357.35884,"total_supply":64469737785.68351,"platform":{"id":1027,"name":"Ethereum","symbol":"ETH","slug":"ethereum","token_address":"0xdac17f958d2ee523a2206206994597c13d831ec7"},"is_active":1,"cmc_rank":3,"is_fiat":0,"last_updated":"2021-07-26T10:27:08.000Z","quote":{"USD":{"price":1.00054201752804,"volume_24h":72259167778.59462,"percent_change_1h":0.02065635,"percent_change_24h":-0.01453608,"percent_change_7d":0.02910011,"percent_change_30d":-0.01523856,"percent_change_60d":-0.09566715,"percent_change_90d":0.03660929,"market_cap":61843834640.91051,"last_updated":"2021-07-26T10:27:08.000Z"}}}}