{"BTC":{"id":1,"name":"Bitcoin","symbol":"BTC","slug":"bitcoin","num_market_pairs":8936,"date_added":"2013-04-28T00:00:00.000Z","tags":["mineable","pow","sha-256","store-of-value","state-channels","coinbase-ventures-portfolio","three-arrows-capital-portfolio","polychain-capital-portfolio","binance-labs-portfolio","arrington-xrp-capital","blockchain-capital-portfolio","boostvc-portfolio","cms-holdings-portfolio","dcg-portfolio","dragonfly-capital-portfolio","electric-capital-portfolio","fabric-ventures-portfolio","framework-ventures","galaxy-digital-portfolio","huobi-capital","alameda-research-portfolio","a16z-portfolio","1confirmation-portfolio","winklevoss-capital","usv-portfolio","placeholder-ventures-portfolio","pantera-capital-portfolio","multicoin-capital-portfolio","paradigm-xzy-screener"],"max_supply":21000000,"circulating_supply":18783462,"total_supply":18783462,"is_active":1,"platform":null,"cmc_rank":1,"is_fiat":0,"last_updated":"2021-08-12T02:39:02.000Z","quote":{"USD":{"price":46179.660899135364,"volume_24h":34724868915.92997,"percent_change_1h":0.43320209,"percent_change_24h":1.49881205,"percent_change_7d":17.46250255,"percent_change_30d":39.24557507,"percent_change_60d":29.64773582,"percent_change_90d":-7.06162996,"market_cap":867413905671.7949,"market_cap_dominance":44.7011,"fully_diluted_market_cap":969772878881.84,"last_updated":"2021-08-12T02:39:02.000Z"}}},"SBD":{"id":1312,"name":"Steem Dollars","symbol":"SBD","slug":"steem-dollars","num_market_pairs":5,"date_added":"2016-07-18T00:00:00.000Z","tags":["media","content-creation","stablecoin"],"max_supply":null,"circulating_supply":8447708.435,"total_supply":8447708.435,"is_active":1,"platform":null,"cmc_rank":428,"is_fiat":0,"last_updated":"2021-08-12T02:39:04.000Z","quote":{"USD":{"price":7.9843986472282,"volume_24h":25382135.41419005,"percent_change_1h":0.23843142,"percent_change_24h":4.5278627,"percent_change_7d":14.68250161,"percent_change_30d":2.27819512,"percent_change_60d":25.79605524,"percent_change_90d":37.01279525,"market_cap":67449871.80059226,"market_cap_dominance":0.0035,"fully_diluted_market_cap":67449871.8,"last_updated":"2021-08-12T02:39:04.000Z"}}},"STEEM":{"id":1230,"name":"Steem","symbol":"STEEM","slug":"steem","num_market_pairs":31,"date_added":"2016-04-18T00:00:00.000Z","tags":["media","content-creation"],"max_supply":null,"circulating_supply":387367362.014,"total_supply":404341456.014,"is_active":1,"platform":null,"cmc_rank":178,"is_fiat":0,"last_updated":"2021-08-12T02:39:03.000Z","quote":{"USD":{"price":0.57161418975535,"volume_24h":14734913.99720505,"percent_change_1h":-0.36618211,"percent_change_24h":5.5182894,"percent_change_7d":15.37899735,"percent_change_30d":28.64026133,"percent_change_60d":45.22029316,"percent_change_90d":-35.76896025,"market_cap":221424680.77529997,"market_cap_dominance":0.0114,"fully_diluted_market_cap":231127313.76,"last_updated":"2021-08-12T02:39:03.000Z"}}},"TRX":{"id":1958,"name":"TRON","symbol":"TRX","slug":"tron","num_market_pairs":520,"date_added":"2017-09-13T00:00:00.000Z","tags":["media","payments","binance-smart-chain"],"max_supply":null,"circulating_supply":71659657369.49,"total_supply":100850743811.662,"is_active":1,"platform":null,"cmc_rank":25,"is_fiat":0,"last_updated":"2021-08-12T02:38:07.000Z","quote":{"USD":{"price":0.08805882176307,"volume_24h":2498726432.7473783,"percent_change_1h":0.51862627,"percent_change_24h":17.65279461,"percent_change_7d":26.41712913,"percent_change_30d":45.41680196,"percent_change_60d":28.35120783,"percent_change_90d":-27.28211082,"market_cap":6310264995.902586,"market_cap_dominance":0.3252,"fully_diluted_market_cap":8880797673.98,"last_updated":"2021-08-12T02:38:07.000Z"}}},"USDT":{"id":825,"name":"Tether","symbol":"USDT","slug":"tether","num_market_pairs":16651,"date_added":"2015-02-25T00:00:00.000Z","tags":["payments","stablecoin","stablecoin-asset-backed","binance-smart-chain","avalanche-ecosystem","solana-ecosystem"],"max_supply":null,"circulating_supply":62944734130.548836,"total_supply":64468847059.56271,"platform":{"id":1027,"name":"Ethereum","symbol":"ETH","slug":"ethereum","token_address":"0xdac17f958d2ee523a2206206994597c13d831ec7"},"is_active":1,"cmc_rank":4,"is_fiat":0,"last_updated":"2021-08-12T02:39:06.000Z","quote":{"USD":{"price":0.99997824280847,"volume_24h":90609730783.7062,"percent_change_1h":-0.02990371,"percent_change_24h":-0.0240427,"percent_change_7d":0.00348632,"percent_change_30d":-0.0478551,"percent_change_60d":-0.11776835,"percent_change_90d":-0.0173643,"market_cap":62943364629.91255,"market_cap_dominance":3.2437,"fully_diluted_market_cap":64467444398.51,"last_updated":"2021-08-12T02:39:06.000Z"}}}}