{"BTC":{"id":1,"name":"Bitcoin","symbol":"BTC","slug":"bitcoin","num_market_pairs":9021,"date_added":"2013-04-28T00:00:00.000Z","tags":["mineable","pow","sha-256","store-of-value","state-channel","coinbase-ventures-portfolio","three-arrows-capital-portfolio","polychain-capital-portfolio","binance-labs-portfolio","blockchain-capital-portfolio","boostvc-portfolio","cms-holdings-portfolio","dcg-portfolio","dragonfly-capital-portfolio","electric-capital-portfolio","fabric-ventures-portfolio","framework-ventures-portfolio","galaxy-digital-portfolio","huobi-capital-portfolio","alameda-research-portfolio","a16z-portfolio","1confirmation-portfolio","winklevoss-capital-portfolio","usv-portfolio","placeholder-ventures-portfolio","pantera-capital-portfolio","multicoin-capital-portfolio","paradigm-portfolio"],"max_supply":21000000,"circulating_supply":18925706,"total_supply":18925706,"is_active":1,"platform":null,"cmc_rank":1,"is_fiat":0,"last_updated":"2022-01-11T05:13:00.000Z","quote":{"USD":{"price":42229.31085013557,"volume_24h":33318324879.756,"volume_change_24h":59.4662,"percent_change_1h":0.10295995,"percent_change_24h":0.18839281,"percent_change_7d":-8.49853858,"percent_change_30d":-13.95639686,"percent_change_60d":-35.05042404,"percent_change_90d":-24.66151641,"market_cap":799219521732.2758,"market_cap_dominance":40.8081,"fully_diluted_market_cap":886815527852.85,"last_updated":"2022-01-11T05:13:00.000Z"}}},"SBD":{"id":1312,"name":"Steem Dollars","symbol":"SBD","slug":"steem-dollars","num_market_pairs":5,"date_added":"2016-07-18T00:00:00.000Z","tags":["media","content-creation","stablecoin"],"max_supply":null,"circulating_supply":10284918.416,"total_supply":10284918.416,"is_active":1,"platform":null,"cmc_rank":590,"is_fiat":0,"last_updated":"2022-01-11T05:13:00.000Z","quote":{"USD":{"price":4.677740762869517,"volume_24h":13149171.31000678,"volume_change_24h":-46.867,"percent_change_1h":0.10295995,"percent_change_24h":-5.23551984,"percent_change_7d":-13.06370254,"percent_change_30d":-18.99182182,"percent_change_60d":-34.90941364,"percent_change_90d":-36.83584451,"market_cap":48110182.11731058,"market_cap_dominance":0.0025,"fully_diluted_market_cap":48110182.12,"last_updated":"2022-01-11T05:13:00.000Z"}}},"STEEM":{"id":1230,"name":"Steem","symbol":"STEEM","slug":"steem","num_market_pairs":32,"date_added":"2016-04-18T00:00:00.000Z","tags":["media","content-creation","web3"],"max_supply":null,"circulating_supply":394951699,"total_supply":409190981,"is_active":1,"platform":null,"cmc_rank":317,"is_fiat":0,"last_updated":"2022-01-11T05:13:00.000Z","quote":{"USD":{"price":0.4209803477893731,"volume_24h":172650532.49546853,"volume_change_24h":-11.9949,"percent_change_1h":-1.17233217,"percent_change_24h":-14.38381944,"percent_change_7d":-4.1454829,"percent_change_30d":-8.11739092,"percent_change_60d":-29.67079419,"percent_change_90d":-29.5760555,"market_cap":166266903.6050238,"market_cap_dominance":0.0085,"fully_diluted_market_cap":172261361.49,"last_updated":"2022-01-11T05:13:00.000Z"}}},"TRX":{"id":1958,"name":"TRON","symbol":"TRX","slug":"tron","num_market_pairs":557,"date_added":"2017-09-13T00:00:00.000Z","tags":["media","payments","tron-ecosystem","binance-smart-chain"],"max_supply":null,"circulating_supply":101842514438.76207,"total_supply":101842514348.39775,"is_active":1,"platform":null,"cmc_rank":28,"is_fiat":0,"last_updated":"2022-01-11T05:13:00.000Z","quote":{"USD":{"price":0.06414756737788237,"volume_24h":1219533364.9135544,"volume_change_24h":30.2432,"percent_change_1h":-0.06598278,"percent_change_24h":-3.99507601,"percent_change_7d":-16.12682776,"percent_change_30d":-29.74876721,"percent_change_60d":-41.95903091,"percent_change_90d":-33.55186497,"market_cap":6532949556.893448,"market_cap_dominance":0.3337,"fully_diluted_market_cap":6532949551.1,"last_updated":"2022-01-11T05:13:00.000Z"}}},"USDT":{"id":825,"name":"Tether","symbol":"USDT","slug":"tether","num_market_pairs":25658,"date_added":"2015-02-25T00:00:00.000Z","tags":["payments","stablecoin","asset-backed-stablecoin","binance-smart-chain","avalanche-ecosystem","solana-ecosystem","moonriver-ecosystem"],"max_supply":null,"circulating_supply":78279163466.97517,"total_supply":82008972933.36424,"platform":{"id":1027,"name":"Ethereum","symbol":"ETH","slug":"ethereum","token_address":"0xdac17f958d2ee523a2206206994597c13d831ec7"},"is_active":1,"cmc_rank":3,"is_fiat":0,"last_updated":"2022-01-11T05:13:00.000Z","quote":{"USD":{"price":1.0002167236554909,"volume_24h":70496822362.33296,"volume_change_24h":47.1747,"percent_change_1h":-0.00324141,"percent_change_24h":-0.00051589,"percent_change_7d":0.01059014,"percent_change_30d":-0.16747728,"percent_change_60d":-0.0424422,"percent_change_90d":0.04367723,"market_cap":78296128413.4305,"market_cap_dominance":3.9978,"fully_diluted_market_cap":82026746217.76,"last_updated":"2022-01-11T05:13:00.000Z"}}}}