{"BTC":{"id":1,"name":"Bitcoin","symbol":"BTC","slug":"bitcoin","num_market_pairs":9000,"date_added":"2013-04-28T00:00:00.000Z","tags":["mineable","pow","sha-256","store-of-value","state-channel","coinbase-ventures-portfolio","three-arrows-capital-portfolio","polychain-capital-portfolio","binance-labs-portfolio","blockchain-capital-portfolio","boostvc-portfolio","cms-holdings-portfolio","dcg-portfolio","dragonfly-capital-portfolio","electric-capital-portfolio","fabric-ventures-portfolio","framework-ventures-portfolio","galaxy-digital-portfolio","huobi-capital-portfolio","alameda-research-portfolio","a16z-portfolio","1confirmation-portfolio","winklevoss-capital-portfolio","usv-portfolio","placeholder-ventures-portfolio","pantera-capital-portfolio","multicoin-capital-portfolio","paradigm-portfolio"],"max_supply":21000000,"circulating_supply":18920181,"total_supply":18920181,"is_active":1,"platform":null,"cmc_rank":1,"is_fiat":0,"last_updated":"2022-01-05T02:45:00.000Z","quote":{"USD":{"price":46340.164908040395,"volume_24h":44417285346.31874,"volume_change_24h":38.0904,"percent_change_1h":0.18113425,"percent_change_24h":0.33357699,"percent_change_7d":-3.35474474,"percent_change_30d":-5.6270503,"percent_change_60d":-23.97950334,"percent_change_90d":-15.80546248,"market_cap":876764307629.9727,"market_cap_dominance":39.3717,"fully_diluted_market_cap":973143463068.85,"last_updated":"2022-01-05T02:45:00.000Z"}}},"SBD":{"id":1312,"name":"Steem Dollars","symbol":"SBD","slug":"steem-dollars","num_market_pairs":5,"date_added":"2016-07-18T00:00:00.000Z","tags":["media","content-creation","stablecoin"],"max_supply":null,"circulating_supply":10228419.912,"total_supply":10228419.912,"is_active":1,"platform":null,"cmc_rank":588,"is_fiat":0,"last_updated":"2022-01-05T02:45:00.000Z","quote":{"USD":{"price":5.431686061009297,"volume_24h":1615007.89030512,"volume_change_24h":-51.6124,"percent_change_1h":0.85272168,"percent_change_24h":0.65265782,"percent_change_7d":-0.5852515,"percent_change_30d":-7.11558079,"percent_change_60d":-27.26673349,"percent_change_90d":-30.50152761,"market_cap":55557565.86216035,"market_cap_dominance":0.0025,"fully_diluted_market_cap":55557565.86,"last_updated":"2022-01-05T02:45:00.000Z"}}},"STEEM":{"id":1230,"name":"Steem","symbol":"STEEM","slug":"steem","num_market_pairs":32,"date_added":"2016-04-18T00:00:00.000Z","tags":["media","content-creation","web3"],"max_supply":null,"circulating_supply":394951699,"total_supply":409190981,"is_active":1,"platform":null,"cmc_rank":330,"is_fiat":0,"last_updated":"2022-01-05T02:45:00.000Z","quote":{"USD":{"price":0.44355964178283447,"volume_24h":19498489.35476673,"volume_change_24h":9.691,"percent_change_1h":0.23750543,"percent_change_24h":0.50847792,"percent_change_7d":2.70211153,"percent_change_30d":-2.45395931,"percent_change_60d":-27.77122484,"percent_change_90d":-31.73435753,"market_cap":175184634.12996185,"market_cap_dominance":0.0079,"fully_diluted_market_cap":181500604.95,"last_updated":"2022-01-05T02:45:00.000Z"}}},"TRX":{"id":1958,"name":"TRON","symbol":"TRX","slug":"tron","num_market_pairs":556,"date_added":"2017-09-13T00:00:00.000Z","tags":["media","payments","tron-ecosystem","binance-smart-chain"],"max_supply":null,"circulating_supply":101851892637.19235,"total_supply":101851891300.82227,"is_active":1,"platform":null,"cmc_rank":27,"is_fiat":0,"last_updated":"2022-01-05T02:45:00.000Z","quote":{"USD":{"price":0.07656696746984783,"volume_24h":1289406996.2373688,"volume_change_24h":-4.8396,"percent_change_1h":0.22418604,"percent_change_24h":0.02040634,"percent_change_7d":-1.818015,"percent_change_30d":-8.10620856,"percent_change_60d":-25.73699674,"percent_change_90d":-19.85201635,"market_cap":7798490550.29434,"market_cap_dominance":0.35,"fully_diluted_market_cap":7798490447.97,"last_updated":"2022-01-05T02:45:00.000Z"}}},"USDT":{"id":825,"name":"Tether","symbol":"USDT","slug":"tether","num_market_pairs":25317,"date_added":"2015-02-25T00:00:00.000Z","tags":["payments","stablecoin","asset-backed-stablecoin","binance-smart-chain","avalanche-ecosystem","solana-ecosystem"],"max_supply":null,"circulating_supply":78437966727.64848,"total_supply":82758976094.03755,"platform":{"id":1027,"name":"Ethereum","symbol":"ETH","slug":"ethereum","token_address":"0xdac17f958d2ee523a2206206994597c13d831ec7"},"is_active":1,"cmc_rank":4,"is_fiat":0,"last_updated":"2022-01-05T02:45:00.000Z","quote":{"USD":{"price":1.000278230607947,"volume_24h":60793398424.81025,"volume_change_24h":8.7635,"percent_change_1h":-0.00091251,"percent_change_24h":-0.01344273,"percent_change_7d":-0.02916977,"percent_change_30d":-0.06166897,"percent_change_60d":-0.06911398,"percent_change_90d":-0.01157096,"market_cap":78459790570.81725,"market_cap_dominance":3.5221,"fully_diluted_market_cap":82782002174.27,"last_updated":"2022-01-05T02:45:00.000Z"}}}}