{"BTC":{"id":1,"name":"Bitcoin","symbol":"BTC","slug":"bitcoin","num_market_pairs":9023,"date_added":"2013-04-28T00:00:00.000Z","tags":["mineable","pow","sha-256","store-of-value","state-channel","coinbase-ventures-portfolio","three-arrows-capital-portfolio","polychain-capital-portfolio","binance-labs-portfolio","blockchain-capital-portfolio","boostvc-portfolio","cms-holdings-portfolio","dcg-portfolio","dragonfly-capital-portfolio","electric-capital-portfolio","fabric-ventures-portfolio","framework-ventures-portfolio","galaxy-digital-portfolio","huobi-capital-portfolio","alameda-research-portfolio","a16z-portfolio","1confirmation-portfolio","winklevoss-capital-portfolio","usv-portfolio","placeholder-ventures-portfolio","pantera-capital-portfolio","multicoin-capital-portfolio","paradigm-portfolio"],"max_supply":21000000,"circulating_supply":18926575,"total_supply":18926575,"is_active":1,"platform":null,"cmc_rank":1,"is_fiat":0,"last_updated":"2022-01-12T04:50:00.000Z","quote":{"USD":{"price":42621.63900129599,"volume_24h":25587364037.004692,"volume_change_24h":-23.0973,"percent_change_1h":0.03120319,"percent_change_24h":0.9436238,"percent_change_7d":-8.17145657,"percent_change_30d":-13.15463802,"percent_change_60d":-33.24811767,"percent_change_90d":-26.24057806,"market_cap":806681647180.9536,"market_cap_dominance":40.1885,"fully_diluted_market_cap":895054419027.22,"last_updated":"2022-01-12T04:50:00.000Z"}}},"SBD":{"id":1312,"name":"Steem Dollars","symbol":"SBD","slug":"steem-dollars","num_market_pairs":5,"date_added":"2016-07-18T00:00:00.000Z","tags":["media","content-creation","stablecoin"],"max_supply":null,"circulating_supply":10294080.726,"total_supply":10294080.726,"is_active":1,"platform":null,"cmc_rank":606,"is_fiat":0,"last_updated":"2022-01-12T04:50:00.000Z","quote":{"USD":{"price":4.60356322852998,"volume_24h":3144384.94111255,"volume_change_24h":-76.789,"percent_change_1h":0.03120319,"percent_change_24h":-1.57153736,"percent_change_7d":-15.05763017,"percent_change_30d":-18.67179072,"percent_change_60d":-36.01673702,"percent_change_90d":-39.431982,"market_cap":47389451.501732804,"market_cap_dominance":0.0024,"fully_diluted_market_cap":47389451.5,"last_updated":"2022-01-12T04:50:00.000Z"}}},"STEEM":{"id":1230,"name":"Steem","symbol":"STEEM","slug":"steem","num_market_pairs":32,"date_added":"2016-04-18T00:00:00.000Z","tags":["media","content-creation","web3"],"max_supply":null,"circulating_supply":394951699,"total_supply":409190981,"is_active":1,"platform":null,"cmc_rank":323,"is_fiat":0,"last_updated":"2022-01-12T04:50:00.000Z","quote":{"USD":{"price":0.41274436644049234,"volume_24h":46171287.18066964,"volume_change_24h":-73.692,"percent_change_1h":-0.17539155,"percent_change_24h":-1.85308967,"percent_change_7d":-7.34807475,"percent_change_30d":-8.09616515,"percent_change_60d":-29.8504931,"percent_change_90d":-35.60356717,"market_cap":163014088.77835104,"market_cap_dominance":0.0081,"fully_diluted_market_cap":168891272.21,"last_updated":"2022-01-12T04:50:00.000Z"}}},"TRX":{"id":1958,"name":"TRON","symbol":"TRX","slug":"tron","num_market_pairs":558,"date_added":"2017-09-13T00:00:00.000Z","tags":["media","payments","tron-ecosystem","binance-smart-chain"],"max_supply":null,"circulating_supply":101840748337.02522,"total_supply":101840749546.03139,"is_active":1,"platform":null,"cmc_rank":28,"is_fiat":0,"last_updated":"2022-01-12T04:50:00.000Z","quote":{"USD":{"price":0.06563547129541407,"volume_24h":961201688.5305412,"volume_change_24h":-20.8882,"percent_change_1h":-0.32273236,"percent_change_24h":2.29792163,"percent_change_7d":-14.48889554,"percent_change_30d":-27.02694291,"percent_change_60d":-39.51257339,"percent_change_90d":-32.89380949,"market_cap":6684365514.178308,"market_cap_dominance":0.333,"fully_diluted_market_cap":6684365593.53,"last_updated":"2022-01-12T04:50:00.000Z"}}},"USDT":{"id":825,"name":"Tether","symbol":"USDT","slug":"tether","num_market_pairs":25750,"date_added":"2015-02-25T00:00:00.000Z","tags":["payments","stablecoin","asset-backed-stablecoin","binance-smart-chain","avalanche-ecosystem","solana-ecosystem","moonriver-ecosystem"],"max_supply":null,"circulating_supply":78391169307.4411,"total_supply":82008978873.83017,"platform":{"id":1027,"name":"Ethereum","symbol":"ETH","slug":"ethereum","token_address":"0xdac17f958d2ee523a2206206994597c13d831ec7"},"is_active":1,"cmc_rank":3,"is_fiat":0,"last_updated":"2022-01-12T04:50:00.000Z","quote":{"USD":{"price":1.0002725124166811,"volume_24h":58573551667.11429,"volume_change_24h":-16.8074,"percent_change_1h":-0.00688599,"percent_change_24h":0.00646769,"percent_change_7d":0.00501845,"percent_change_30d":-0.11941303,"percent_change_60d":-0.0115675,"percent_change_90d":0.03781169,"market_cap":78412531874.43553,"market_cap_dominance":3.9072,"fully_diluted_market_cap":82031327338.85,"last_updated":"2022-01-12T04:50:00.000Z"}}}}