[{"status":"OK","datetime":"2021-08-22T06:55:58.403153","source_commit":"ae6c6c77601436e496a8816ece2cbc6e26fbe3c2","docker_tag":"latest","jussi_num":56580288,"ping":199,"url":"https://api.steemit.com"},{"status":"OK","datetime":"2021-08-22T06:55:58.395004","source_commit":"ae6c6c77601436e496a8816ece2cbc6e26fbe3c2","docker_tag":"latest","jussi_num":56580288,"ping":190,"url":"https://api.steemitdev.com"},{"status":"OK","datetime":"2021-08-22T06:55:58.590676","source_commit":"ae6c6c77601436e496a8816ece2cbc6e26fbe3c2","docker_tag":"latest","jussi_num":56580288,"ping":431,"url":"https://api.justyy.com"},{"status":"OK","datetime":"2021-08-22T06:55:58.434545","source_commit":"ae6c6c77601436e496a8816ece2cbc6e26fbe3c2","docker_tag":"latest","jussi_num":56580288,"__version__":{"id":0,"jsonrpc":"2.0","result":{"blockchain_version":"0.23.0","steem_revision":"46c7d93db350e8b031a81626e727c92b27d7348b","fc_revision":"46c7d93db350e8b031a81626e727c92b27d7348b"}},"__server__":"https://api.steemit.com","ping":234,"url":"https://e51ewpb9dk.execute-api.us-east-1.amazonaws.com/release"},{"status":"OK","datetime":"2021-08-22T06:55:58.532952","source_commit":"ae6c6c77601436e496a8816ece2cbc6e26fbe3c2","docker_tag":"latest","jussi_num":56579918,"ping":365,"url":"https://api.steemyy.com"},{"status":"OK","datetime":"2021-08-22T06:55:58.482125","source_commit":"ae6c6c77601436e496a8816ece2cbc6e26fbe3c2","docker_tag":"latest","jussi_num":56580288,"ping":279,"url":"https://api.steemzzang.com"},{"status":"OK","datetime":"2021-08-22T06:55:59.466377","source_commit":"ae6c6c77601436e496a8816ece2cbc6e26fbe3c2","docker_tag":"latest","jussi_num":56580285,"__version__":{"id":0,"jsonrpc":"2.0","result":{"blockchain_version":"0.23.0","steem_revision":"4004f2845334b8283968088b88caebfab7b71c6b","fc_revision":"4004f2845334b8283968088b88caebfab7b71c6b"}},"__server__":"https://api.steem.fans","ping":1374,"url":"https://x68bp3mesd.execute-api.ap-northeast-1.amazonaws.com/release"},{"status":"OK","datetime":"2021-08-22T06:55:58.782805","source_commit":"ae6c6c77601436e496a8816ece2cbc6e26fbe3c2","docker_tag":"latest","jussi_num":56580285,"ping":624,"url":"https://cn.steems.top"},{"status":"OK","datetime":"2021-08-22T06:55:58.738448","source_commit":"ae6c6c77601436e496a8816ece2cbc6e26fbe3c2","docker_tag":"latest","jussi_num":56580288,"__server__":"https://api.justyy.com","__version__":{"id":0,"jsonrpc":"2.0","result":{"blockchain_version":"0.23.1","steem_revision":"46c7d93db350e8b031a81626e727c92b27d7348b","fc_revision":"46c7d93db350e8b031a81626e727c92b27d7348b"}},"ping":590,"url":"https://justyy.azurewebsites.net/api/steem"},{"status":"OK","datetime":"2021-08-22T06:55:58.612792","source_commit":"ae6c6c77601436e496a8816ece2cbc6e26fbe3c2","docker_tag":"latest","jussi_num":56580288,"__server__":"https://api.steemit.com","__version__":{"id":0,"jsonrpc":"2.0","result":{"blockchain_version":"0.23.0","steem_revision":"46c7d93db350e8b031a81626e727c92b27d7348b","fc_revision":"46c7d93db350e8b031a81626e727c92b27d7348b"}},"__country__":"US","ping":432,"url":"https://steem.justyy.workers.dev"},{"status":"OK","datetime":"2021-08-22T06:55:58.573764","source_commit":"ae6c6c77601436e496a8816ece2cbc6e26fbe3c2","docker_tag":"latest","jussi_num":56580285,"ping":412,"url":"https://steem.ecosynthesizer.com"},{"status":"OK","datetime":"2021-08-22T06:55:59.825921","source_commit":"ae6c6c77601436e496a8816ece2cbc6e26fbe3c2","docker_tag":"latest","jussi_num":56580288,"ping":1739,"url":"https://steem.61bts.com"},{"status":"OK","datetime":"2021-08-22T06:55:58.808861","source_commit":"ae6c6c77601436e496a8816ece2cbc6e26fbe3c2","docker_tag":"latest","jussi_num":56580285,"ping":651,"url":"https://api.steem.buzz"},{"status":"OK","datetime":"2021-08-22T06:55:59.219535","source_commit":"ae6c6c77601436e496a8816ece2cbc6e26fbe3c2","docker_tag":"latest","jussi_num":56580285,"ping":1152,"url":"https://api.steem.fans"}]